builtin/__init__.py
builtin/troll.py
trollpy-0.1.0.dist-info/LICENSE
trollpy-0.1.0.dist-info/WHEEL
trollpy-0.1.0.dist-info/METADATA
trollpy-0.1.0.dist-info/RECORD
