Metadata-Version: 2.1
Name: trollpy
Version: 0.1.0
Summary: A Python library for overriding functions/classes and trolling others
Home-page: https://github.com/zahtec/trollpy
License: MIT
Keywords: troll,trolling,override,overriding
Author: zahtec
Requires-Python: >=3.10,<4.0
Classifier: Intended Audience :: Developers
Classifier: License :: OSI Approved :: MIT License
Classifier: Natural Language :: English
Classifier: Operating System :: OS Independent
Classifier: Programming Language :: Python :: 3
Classifier: Programming Language :: Python :: 3.10
Classifier: Programming Language :: Python :: 3.10
Project-URL: Bug Tracker, https://github.com/zahtec/trollpy/issues
Project-URL: Documentation, https://github.com/zahtec/trollpy/wiki
Project-URL: Repository, https://github.com/zahtec/trollpy
